
  [
        {
            "title": "Samsung Semiconductor",
            "city": "Austin",
            "link": "https://wehireheroes.com/company/410/samsung-austin-semiconductor/"
        },
         {
            "title": "Chevron Phillips Chemical Company",
            "city": "Houston",
            "link": "https://petrochemworks.com/employers/cpchem"
        },
         {
            "title": "Honeywell",
            "city": "Lubbock",
            "link": "http://www.jobsintrucks.com/cgi-local/driversearch.cgi?action=ViewJobDetails&TypeOfUser=browse&JobIndNum=7575802&Source=indeed-sponsored"
        },
         {
            "title": "US Express",
            "city": "Amarillo",
            "link": "http://www.findatruckerjob.com/jobs/company=US+Xpress&l=Amarillo+TX&JobId=Cb-4KGNO4WCzY3hsKs-VmQ?utm_source=indeed"
        },

         {
            "title": "Union Pacific",
            "city": "Fort Worth",
            "link": "https://up.jobs/job/opening/Electrician%20-%20Diesel%20Engines/Fort%20Worth/TX/081282?jsl=27559965"
        },
         {
            "title": "Malin Raymond Co",
            "city": "Dallas",
            "link": "https://recruiting.adp.com/srccar/public/RTI.home?c=1127807&d=MalinExternalCareerCenter&rb=???&r=5000171341706"
        },
         {
            "title": "Aramark",
            "city": "Waco",
            "link": "http://www.aramark.com/careers"
        },
         {
            "title": "DuPont",
            "city": "Galveston",
            "link": "http://careers.dupont.com/jobsearch/#All~Job~Organizations|All~Job~Categories|All~Job~Locations|1|1|1||t-ASC|1"
        },
         {
            "title": "Endura Production Corps",
            "city": "Midland",
            "link": "http://www.enduraproductscorp.com/employment.php"
        },
         {
            "title": "USAA Jobs",
            "city": "San Antonio",
            "link": "https://search.usaajobs.com/us/en-us/find/Veterans-Jobs/XjfrP-jfr64"
        },
         {
            "title": "Mobile Mini",
            "city": "Corpus Christi",
            "link": "https://jobs.mobilemini.com/"
        },
         {
            "title": "Apex",
            "city": "Laredo",
            "link": "http://apexcareers.com/"
        },
         {
            "title": "C.R. England",
            "city": "Brownsville",
            "link": "http://drivecre.com/recent-grads/?id=BAY_IND_RECENT_GRADS&rs=7000&aasi=2"
        },
         {
            "title": "TPC Group",
            "city": "Harlingen",
            "link": "http://www.tpcgrp.com/tpc-group/career-center-5.html"
        },
        {
            "title": "Solar City",
            "city": "El Paso",
            "link": "https://solarcity.wd1.myworkdayjobs.com/en-US/01/job/TX-El-Paso/Solar-Sales---Energy-Specialist_R-16350-9?source=Indeed"
        },
        {
            "title": "Shoppa's Material Handling",
            "city": "Odessa",
            "link": "https://recruiting.ultipro.com/SHO1007/JobBoard/eb277497-604c-a5e9-c370-614cf6e65122/OpportunityDetail?opportunityId=1c947080-e1d7-4bb1-a56e-f07794ad0c08"
        },
    ]